ofunctions-2.8.0-py3.12-nspkg.pth
ofunctions/bisection/__init__.py
ofunctions/checksums/__init__.py
ofunctions/csv/__init__.py
ofunctions/delayed_keyboardinterrupt/__init__.py
ofunctions/file_utils/__init__.py
ofunctions/json_sanitize/__init__.py
ofunctions/logger_utils/__init__.py
ofunctions/mailer/__init__.py
ofunctions/misc/__init__.py
ofunctions/network/__init__.py
ofunctions/platform/__init__.py
ofunctions/process/__init__.py
ofunctions/random/__init__.py
ofunctions/requestor/__init__.py
ofunctions/service_control/__init__.py
ofunctions/string_handling/__init__.py
ofunctions/threading/__init__.py
ofunctions-2.8.0.dist-info/LICENSE
ofunctions-2.8.0.dist-info/METADATA
ofunctions-2.8.0.dist-info/WHEEL
ofunctions-2.8.0.dist-info/namespace_packages.txt
ofunctions-2.8.0.dist-info/top_level.txt
ofunctions-2.8.0.dist-info/RECORD
